README.rst
setup.py
psquery/__init__.py
psquery/config.py
psquery/query_client.py
psquery.egg-info/PKG-INFO
psquery.egg-info/SOURCES.txt
psquery.egg-info/dependency_links.txt
psquery.egg-info/entry_points.txt
psquery.egg-info/requires.txt
psquery.egg-info/top_level.txt