Metadata-Version: 1.1
Name: psquery
Version: 0.0.2
Summary: Predictive Services Query Client
Home-page: https://github.com/turi-code/psquery
Author: Turi, Inc.
Author-email: contact@turi.com
License: LICENSE
Keywords: turi graphlab predictive services
Platform: UNKNOWN
Classifier: Development Status :: 3 - Alpha
Classifier: Intended Audience :: Developers
Classifier: License :: OSI Approved :: BSD License
Classifier: Programming Language :: Python :: 2.7
Classifier: Topic :: Scientific/Engineering
Classifier: Topic :: Scientific/Engineering :: Information Analysis
